streamline/__init__.py
streamline/router.py
streamline/trie.py
streamline_cwf-0.1.dist-info/METADATA
streamline_cwf-0.1.dist-info/WHEEL
streamline_cwf-0.1.dist-info/top_level.txt
streamline_cwf-0.1.dist-info/RECORD
